ratellmiter/__init__.py
ratellmiter/open_graph.sh
ratellmiter/rate_llmiter.py
ratellmiter/test_ratellmiter.py
rateLLMiter_ai-0.1.23.dist-info/LICENSE
rateLLMiter_ai-0.1.23.dist-info/METADATA
rateLLMiter_ai-0.1.23.dist-info/WHEEL
rateLLMiter_ai-0.1.23.dist-info/entry_points.txt
rateLLMiter_ai-0.1.23.dist-info/top_level.txt
rateLLMiter_ai-0.1.23.dist-info/RECORD
