Metadata-Version: 2.2
Name: rateLLMiter-ai
Version: 0.1.23
Summary: LLM ratelimiter for Python.
Author-email: Tom Burns <public@llmonpy.ai>
License: MIT License
Project-URL: Homepage, https://github.com/llmonpy/ratellmiter
Project-URL: Issues, https://github.com/llmonpy/ratellmiter/issues
Classifier: Programming Language :: Python :: 3
Classifier: License :: OSI Approved :: MIT License
Classifier: Operating System :: OS Independent
Requires-Python: >=3.12
License-File: LICENSE
Requires-Dist: matplotlib
